{
  "type": "cdl",
  "project": "dcclt",
  "source": "http://oracc.org/dcclt",
  "license": "This data is released under the CC0 license",
  "license-url": "https://creativecommons.org/publicdomain/zero/1.0/",
  "more-info": "http://oracc.org/doc/opendata/",
  "UTC-timestamp": "2017-06-21T22:13:33",
  "textid": "P429498",
  "cdl": [
    {
      "node": "c",
      "type": "text",
      "id": "P429498.U0",
      "cdl": [
        {
          "node": "d",
          "subtype": "tablet",
          "type": "tablet",
          "ref": "P429498.x1285.1",
          "label": "x1285"
        },
        {
          "node": "d",
          "subtype": "obverse",
          "type": "obverse",
          "ref": "P429498.o.2",
          "label": "o"
        },
        {
          "node": "d",
          "subtype": "column 1o '",
          "type": "column",
          "ref": "P429498.o.i_.3",
          "n": "1",
          "label": "o i'"
        },
        {
          "node": "d",
          "type": "nonx",
          "ref": "P429498.4",
          "strict": "0",
          "extent": "beginning",
          "state": "missing"
        },
        {
          "node": "c",
          "type": "discourse",
          "subtype": "body",
          "id": "P429498.U1",
          "cdl": [
            {
              "node": "c",
              "type": "sentence",
              "id": "P429498.U2",
              "label": "o i' 1' - o ii' 17'",
              "cdl": [
                {
                  "node": "d",
                  "type": "line-start",
                  "ref": "P429498.5",
                  "n": "1'",
                  "label": "o i' 1'"
                },
                {
                  "node": "d",
                  "type": "cell-start"
                },
                {
                  "node": "d",
                  "type": "field-start",
                  "subtype": "wp"
                },
                {
                  "node": "l",
                  "frag": "[...]",
                  "id": "P429498.l2fddf",
                  "ref": "P429498.5.1",
                  "inst": "%sux:x=",
                  "f": {
                    "lang": "sux",
                    "form": "x",
                    "gdl": [
                      {
                        "x": "ellipsis",
                        "id": "P429498.5.1.0",
                        "breakStart": "1",
                        "break": "missing",
                        "o": "]",
                        "breakEnd": "P429498.5.1.0"
                      }
                    ]
                  }
                },
                {
                  "node": "d",
                  "type": "field-end",
                  "subtype": "wp"
                },
                {
                  "node": "d",
                  "type": "cell-end"
                },
                {
                  "node": "d",
                  "type": "cell-start"
                },
                {
                  "node": "d",
                  "type": "field-start",
                  "subtype": "eq"
                },
                {
                  "node": "l",
                  "frag": "[...]-⸢x⸣",
                  "id": "P429498.l2fde0",
                  "ref": "P429498.5.2",
                  "inst": "%akk-x-mbperi:x-x=",
                  "f": {
                    "lang": "akk-x-mbperi",
                    "form": "x-x",
                    "gdl": [
                      {
                        "x": "ellipsis",
                        "id": "P429498.5.2.0",
                        "breakStart": "1",
                        "break": "missing",
                        "o": "]",
                        "breakEnd": "P429498.5.2.0",
                        "delim": "-"
                      },
                      {
                        "v": "x",
                        "id": "P429498.5.2.1",
                        "break": "damaged",
                        "ho": "1",
                        "hc": "1"
                      }
                    ]
                  }
                },
                {
                  "node": "d",
                  "type": "field-end",
                  "subtype": "eq"
                },
                {
                  "node": "d",
                  "type": "cell-end"
                },
                {
                  "node": "d",
                  "type": "line-start",
                  "ref": "P429498.6",
                  "n": "2'",
                  "label": "o i' 2'"
                },
                {
                  "node": "d",
                  "type": "cell-start"
                },
                {
                  "node": "d",
                  "type": "field-start",
                  "subtype": "wp"
                },
                {
                  "node": "l",
                  "frag": "[...]",
                  "id": "P429498.l2fde1",
                  "ref": "P429498.6.1",
                  "inst": "%sux:x=",
                  "f": {
                    "lang": "sux",
                    "form": "x",
                    "gdl": [
                      {
                        "x": "ellipsis",
                        "id": "P429498.6.1.0",
                        "breakStart": "1",
                        "break": "missing",
                        "o": "]",
                        "breakEnd": "P429498.6.1.0"
                      }
                    ]
                  }
                },
                {
                  "node": "d",
                  "type": "field-end",
                  "subtype": "wp"
                },
                {
                  "node": "d",
                  "type": "cell-end"
                },
                {
                  "node": "d",
                  "type": "cell-start"
                },
                {
                  "node": "d",
                  "type": "field-start",
                  "subtype": "eq"
                },
                {
                  "node": "l",
                  "frag": "[...]",
                  "id": "P429498.l2fde2",
                  "ref": "P429498.6.2",
                  "inst": "%akk-x-mbperi:x=",
                  "f": {
                    "lang": "akk-x-mbperi",
                    "form": "x",
                    "gdl": [
                      {
                        "x": "ellipsis",
                        "id": "P429498.6.2.0",
                        "breakStart": "1",
                        "break": "missing",
                        "o": "]",
                        "breakEnd": "P429498.6.2.0"
                      }
                    ]
                  }
                },
                {
                  "node": "d",
                  "type": "field-end",
                  "subtype": "eq"
                },
                {
                  "node": "d",
                  "type": "cell-end"
                },
                {
                  "node": "d",
                  "type": "line-start",
                  "ref": "P429498.7",
                  "n": "3'",
                  "label": "o i' 3'"
                },
                {
                  "node": "d",
                  "type": "cell-start"
                },
                {
                  "node": "d",
                  "type": "field-start",
                  "subtype": "wp"
                },
                {
                  "node": "l",
                  "frag": "[...]",
                  "id": "P429498.l2fde3",
                  "ref": "P429498.7.1",
                  "inst": "%sux:x=",
                  "f": {
                    "lang": "sux",
                    "form": "x",
                    "gdl": [
                      {
                        "x": "ellipsis",
                        "id": "P429498.7.1.0",
                        "breakStart": "1",
                        "break": "missing",
                        "o": "]",
                        "breakEnd": "P429498.7.1.0"
                      }
                    ]
                  }
                },
                {
                  "node": "d",
                  "type": "field-end",
                  "subtype": "wp"
                },
                {
                  "node": "d",
                  "type": "cell-end"
                },
                {
                  "node": "d",
                  "type": "cell-start"
                },
                {
                  "node": "d",
                  "type": "field-start",
                  "subtype": "eq"
                },
                {
                  "node": "l",
                  "frag": "[...]",
                  "id": "P429498.l2fde4",
                  "ref": "P429498.7.2",
                  "inst": "%akk-x-mbperi:x=",
                  "f": {
                    "lang": "akk-x-mbperi",
                    "form": "x",
                    "delim": " ",
                    "gdl": [
                      {
                        "x": "ellipsis",
                        "id": "P429498.7.2.0",
                        "breakStart": "1",
                        "break": "missing",
                        "o": "]",
                        "breakEnd": "P429498.7.2.0"
                      }
                    ]
                  }
                },
                {
                  "node": "l",
                  "frag": "⸢ia⸣-ar-hi",
                  "id": "P429498.l2fde5",
                  "ref": "P429498.7.3",
                  "inst": "%akk-x-mbperi:ia-ar-hi=",
                  "f": {
                    "lang": "akk-x-mbperi",
                    "form": "ia-ar-hi",
                    "gdl": [
                      {
                        "v": "ia",
                        "id": "P429498.7.3.0",
                        "break": "damaged",
                        "ho": "1",
                        "delim": "-",
                        "hc": "1"
                      },
                      {
                        "v": "ar",
                        "id": "P429498.7.3.1",
                        "delim": "-"
                      },
                      {
                        "v": "hi",
                        "id": "P429498.7.3.2"
                      }
                    ]
                  }
                },
                {
                  "node": "d",
                  "type": "field-end",
                  "subtype": "eq"
                },
                {
                  "node": "d",
                  "type": "cell-end"
                },
                {
                  "node": "d",
                  "type": "line-start",
                  "ref": "P429498.8",
                  "n": "4'",
                  "label": "o i' 4'"
                },
                {
                  "node": "d",
                  "type": "cell-start"
                },
                {
                  "node": "d",
                  "type": "field-start",
                  "subtype": "wp"
                },
                {
                  "node": "l",
                  "frag": "[...]",
                  "id": "P429498.l2fde6",
                  "ref": "P429498.8.1",
                  "inst": "%sux:x=",
                  "f": {
                    "lang": "sux",
                    "form": "x",
                    "gdl": [
                      {
                        "x": "ellipsis",
                        "id": "P429498.8.1.0",
                        "breakStart": "1",
                        "break": "missing",
                        "o": "]",
                        "breakEnd": "P429498.8.1.0"
                      }
                    ]
                  }
                },
                {
                  "node": "d",
                  "type": "field-end",
                  "subtype": "wp"
                },
                {
                  "node": "d",
                  "type": "cell-end"
                },
                {
                  "node": "d",
                  "type": "cell-start"
                },
                {
                  "node": "d",
                  "type": "field-start",
                  "subtype": "eq"
                },
                {
                  "node": "l",
                  "frag": "[...]-⸢x⸣-bu",
                  "id": "P429498.l2fde7",
                  "ref": "P429498.8.2",
                  "inst": "%akk-x-mbperi:x-x-bu=",
                  "f": {
                    "lang": "akk-x-mbperi",
                    "form": "x-x-bu",
                    "gdl": [
                      {
                        "x": "ellipsis",
                        "id": "P429498.8.2.0",
                        "breakStart": "1",
                        "break": "missing",
                        "o": "]",
                        "breakEnd": "P429498.8.2.0",
                        "delim": "-"
                      },
                      {
                        "v": "x",
                        "id": "P429498.8.2.1",
                        "break": "damaged",
                        "ho": "1",
                        "delim": "-",
                        "hc": "1"
                      },
                      {
                        "v": "bu",
                        "id": "P429498.8.2.2"
                      }
                    ]
                  }
                },
                {
                  "node": "d",
                  "type": "field-end",
                  "subtype": "eq"
                },
                {
                  "node": "d",
                  "type": "cell-end"
                },
                {
                  "node": "d",
                  "type": "line-start",
                  "ref": "P429498.9",
                  "n": "5'",
                  "label": "o i' 5'"
                },
                {
                  "node": "d",
                  "type": "cell-start"
                },
                {
                  "node": "d",
                  "type": "field-start",
                  "subtype": "wp"
                },
                {
                  "node": "l",
                  "frag": "[...]",
                  "id": "P429498.l2fde8",
                  "ref": "P429498.9.1",
                  "inst": "%sux:x=",
                  "f": {
                    "lang": "sux",
                    "form": "x",
                    "gdl": [
                      {
                        "x": "ellipsis",
                        "id": "P429498.9.1.0",
                        "breakStart": "1",
                        "break": "missing",
                        "o": "]",
                        "breakEnd": "P429498.9.1.0"
                      }
                    ]
                  }
                },
                {
                  "node": "d",
                  "type": "field-end",
                  "subtype": "wp"
                },
                {
                  "node": "d",
                  "type": "cell-end"
                },
                {
                  "node": "d",
                  "type": "cell-start"
                },
                {
                  "node": "d",
                  "type": "field-start",
                  "subtype": "eq"
                },
                {
                  "node": "l",
                  "frag": "[...]-ti-hu-u₂",
                  "id": "P429498.l2fde9",
                  "ref": "P429498.9.2",
                  "inst": "%akk-x-mbperi:x-ti-hu-u₂=",
                  "f": {
                    "lang": "akk-x-mbperi",
                    "form": "x-ti-hu-u₂",
                    "gdl": [
                      {
                        "x": "ellipsis",
                        "id": "P429498.9.2.0",
                        "breakStart": "1",
                        "break": "missing",
                        "o": "]",
                        "breakEnd": "P429498.9.2.0",
                        "delim": "-"
                      },
                      {
                        "v": "ti",
                        "id": "P429498.9.2.1",
                        "delim": "-"
                      },
                      {
                        "v": "hu",
                        "id": "P429498.9.2.2",
                        "delim": "-"
                      },
                      {
                        "v": "u₂",
                        "id": "P429498.9.2.3"
                      }
                    ]
                  }
                },
                {
                  "node": "d",
                  "type": "field-end",
                  "subtype": "eq"
                },
                {
                  "node": "d",
                  "type": "cell-end"
                },
                {
                  "node": "d",
                  "type": "line-start",
                  "ref": "P429498.10",
                  "n": "6'",
                  "label": "o i' 6'"
                },
                {
                  "node": "d",
                  "type": "cell-start"
                },
                {
                  "node": "d",
                  "type": "field-start",
                  "subtype": "wp"
                },
                {
                  "node": "l",
                  "frag": "[...]",
                  "id": "P429498.l2fdea",
                  "ref": "P429498.10.1",
                  "inst": "%sux:x=",
                  "f": {
                    "lang": "sux",
                    "form": "x",
                    "gdl": [
                      {
                        "x": "ellipsis",
                        "id": "P429498.10.1.0",
                        "breakStart": "1",
                        "break": "missing",
                        "o": "]",
                        "breakEnd": "P429498.10.1.0"
                      }
                    ]
                  }
                },
                {
                  "node": "d",
                  "type": "field-end",
                  "subtype": "wp"
                },
                {
                  "node": "d",
                  "type": "cell-end"
                },
                {
                  "node": "d",
                  "type": "cell-start"
                },
                {
                  "node": "d",
                  "type": "field-start",
                  "subtype": "eq"
                },
                {
                  "node": "l",
                  "frag": "[...]-⸢x⸣-hu",
                  "id": "P429498.l2fdeb",
                  "ref": "P429498.10.2",
                  "inst": "%akk-x-mbperi:x-x-hu=",
                  "f": {
                    "lang": "akk-x-mbperi",
                    "form": "x-x-hu",
                    "gdl": [
                      {
                        "x": "ellipsis",
                        "id": "P429498.10.2.0",
                        "breakStart": "1",
                        "break": "missing",
                        "o": "]",
                        "breakEnd": "P429498.10.2.0",
                        "delim": "-"
                      },
                      {
                        "v": "x",
                        "id": "P429498.10.2.1",
                        "break": "damaged",
                        "ho": "1",
                        "delim": "-",
                        "hc": "1"
                      },
                      {
                        "v": "hu",
                        "id": "P429498.10.2.2"
                      }
                    ]
                  }
                },
                {
                  "node": "d",
                  "type": "field-end",
                  "subtype": "eq"
                },
                {
                  "node": "d",
                  "type": "cell-end"
                },
                {
                  "node": "d",
                  "type": "line-start",
                  "ref": "P429498.11",
                  "n": "7'",
                  "label": "o i' 7'"
                },
                {
                  "node": "d",
                  "type": "cell-start"
                },
                {
                  "node": "d",
                  "type": "field-start",
                  "subtype": "wp"
                },
                {
                  "node": "l",
                  "frag": "[...]",
                  "id": "P429498.l2fdec",
                  "ref": "P429498.11.1",
                  "inst": "%sux:x=",
                  "f": {
                    "lang": "sux",
                    "form": "x",
                    "gdl": [
                      {
                        "x": "ellipsis",
                        "id": "P429498.11.1.0",
                        "breakStart": "1",
                        "break": "missing",
                        "o": "]",
                        "breakEnd": "P429498.11.1.0"
                      }
                    ]
                  }
                },
                {
                  "node": "d",
                  "type": "field-end",
                  "subtype": "wp"
                },
                {
                  "node": "d",
                  "type": "cell-end"
                },
                {
                  "node": "d",
                  "type": "cell-start"
                },
                {
                  "node": "d",
                  "type": "field-start",
                  "subtype": "eq"
                },
                {
                  "node": "l",
                  "frag": "[...]-bu",
                  "id": "P429498.l2fded",
                  "ref": "P429498.11.2",
                  "inst": "%akk-x-mbperi:x-bu=",
                  "f": {
                    "lang": "akk-x-mbperi",
                    "form": "x-bu",
                    "gdl": [
                      {
                        "x": "ellipsis",
                        "id": "P429498.11.2.0",
                        "breakStart": "1",
                        "break": "missing",
                        "o": "]",
                        "breakEnd": "P429498.11.2.0",
                        "delim": "-"
                      },
                      {
                        "v": "bu",
                        "id": "P429498.11.2.1"
                      }
                    ]
                  }
                },
                {
                  "node": "d",
                  "type": "field-end",
                  "subtype": "eq"
                },
                {
                  "node": "d",
                  "type": "cell-end"
                },
                {
                  "node": "d",
                  "type": "line-start",
                  "ref": "P429498.12",
                  "n": "8'",
                  "label": "o i' 8'"
                },
                {
                  "node": "d",
                  "type": "cell-start"
                },
                {
                  "node": "d",
                  "type": "field-start",
                  "subtype": "wp"
                },
                {
                  "node": "l",
                  "frag": "[...]",
                  "id": "P429498.l2fdee",
                  "ref": "P429498.12.1",
                  "inst": "%sux:x=",
                  "f": {
                    "lang": "sux",
                    "form": "x",
                    "gdl": [
                      {
                        "x": "ellipsis",
                        "id": "P429498.12.1.0",
                        "breakStart": "1",
                        "break": "missing",
                        "o": "]",
                        "breakEnd": "P429498.12.1.0"
                      }
                    ]
                  }
                },
                {
                  "node": "d",
                  "type": "field-end",
                  "subtype": "wp"
                },
                {
                  "node": "d",
                  "type": "cell-end"
                },
                {
                  "node": "d",
                  "type": "cell-start"
                },
                {
                  "node": "d",
                  "type": "field-start",
                  "subtype": "eq"
                },
                {
                  "node": "l",
                  "frag": "[...]-lu",
                  "id": "P429498.l2fdef",
                  "ref": "P429498.12.2",
                  "inst": "%akk-x-mbperi:x-lu=",
                  "f": {
                    "lang": "akk-x-mbperi",
                    "form": "x-lu",
                    "gdl": [
                      {
                        "x": "ellipsis",
                        "id": "P429498.12.2.0",
                        "breakStart": "1",
                        "break": "missing",
                        "o": "]",
                        "breakEnd": "P429498.12.2.0",
                        "delim": "-"
                      },
                      {
                        "v": "lu",
                        "id": "P429498.12.2.1",
                        "queried": "1"
                      }
                    ]
                  }
                },
                {
                  "node": "d",
                  "type": "field-end",
                  "subtype": "eq"
                },
                {
                  "node": "d",
                  "type": "cell-end"
                },
                {
                  "node": "d",
                  "type": "line-start",
                  "ref": "P429498.13",
                  "n": "9'",
                  "label": "o i' 9'"
                },
                {
                  "node": "d",
                  "type": "cell-start"
                },
                {
                  "node": "d",
                  "type": "field-start",
                  "subtype": "wp"
                },
                {
                  "node": "l",
                  "frag": "[...]",
                  "id": "P429498.l2fdf0",
                  "ref": "P429498.13.1",
                  "inst": "%sux:x=",
                  "f": {
                    "lang": "sux",
                    "form": "x",
                    "gdl": [
                      {
                        "x": "ellipsis",
                        "id": "P429498.13.1.0",
                        "breakStart": "1",
                        "break": "missing",
                        "o": "]",
                        "breakEnd": "P429498.13.1.0"
                      }
                    ]
                  }
                },
                {
                  "node": "d",
                  "type": "field-end",
                  "subtype": "wp"
                },
                {
                  "node": "d",
                  "type": "cell-end"
                },
                {
                  "node": "d",
                  "type": "cell-start"
                },
                {
                  "node": "d",
                  "type": "field-start",
                  "subtype": "eq"
                },
                {
                  "node": "l",
                  "frag": "[...]-ri-ku",
                  "id": "P429498.l2fdf1",
                  "ref": "P429498.13.2",
                  "inst": "%akk-x-mbperi:x-ri-ku=",
                  "f": {
                    "lang": "akk-x-mbperi",
                    "form": "x-ri-ku",
                    "gdl": [
                      {
                        "x": "ellipsis",
                        "id": "P429498.13.2.0",
                        "breakStart": "1",
                        "break": "missing",
                        "o": "]",
                        "breakEnd": "P429498.13.2.0",
                        "delim": "-"
                      },
                      {
                        "v": "ri",
                        "id": "P429498.13.2.1",
                        "delim": "-"
                      },
                      {
                        "v": "ku",
                        "id": "P429498.13.2.2"
                      }
                    ]
                  }
                },
                {
                  "node": "d",
                  "type": "field-end",
                  "subtype": "eq"
                },
                {
                  "node": "d",
                  "type": "cell-end"
                },
                {
                  "node": "d",
                  "type": "line-start",
                  "ref": "P429498.14",
                  "n": "10'",
                  "label": "o i' 10'"
                },
                {
                  "node": "d",
                  "type": "cell-start"
                },
                {
                  "node": "d",
                  "type": "field-start",
                  "subtype": "wp"
                },
                {
                  "node": "l",
                  "frag": "[...]",
                  "id": "P429498.l2fdf2",
                  "ref": "P429498.14.1",
                  "inst": "%sux:x=",
                  "f": {
                    "lang": "sux",
                    "form": "x",
                    "gdl": [
                      {
                        "x": "ellipsis",
                        "id": "P429498.14.1.0",
                        "breakStart": "1",
                        "break": "missing",
                        "o": "]",
                        "breakEnd": "P429498.14.1.0"
                      }
                    ]
                  }
                },
                {
                  "node": "d",
                  "type": "field-end",
                  "subtype": "wp"
                },
                {
                  "node": "d",
                  "type": "cell-end"
                },
                {
                  "node": "d",
                  "type": "cell-start"
                },
                {
                  "node": "d",
                  "type": "field-start",
                  "subtype": "eq"
                },
                {
                  "node": "l",
                  "frag": "[...]-⸢x⸣-ta-lu",
                  "id": "P429498.l2fdf3",
                  "ref": "P429498.14.2",
                  "inst": "%akk-x-mbperi:x-x-ta-lu=",
                  "f": {
                    "lang": "akk-x-mbperi",
                    "form": "x-x-ta-lu",
                    "gdl": [
                      {
                        "x": "ellipsis",
                        "id": "P429498.14.2.0",
                        "breakStart": "1",
                        "break": "missing",
                        "o": "]",
                        "breakEnd": "P429498.14.2.0",
                        "delim": "-"
                      },
                      {
                        "v": "x",
                        "id": "P429498.14.2.1",
                        "break": "damaged",
                        "ho": "1",
                        "delim": "-",
                        "hc": "1"
                      },
                      {
                        "v": "ta",
                        "id": "P429498.14.2.2",
                        "delim": "-"
                      },
                      {
                        "v": "lu",
                        "id": "P429498.14.2.3",
                        "queried": "1"
                      }
                    ]
                  }
                },
                {
                  "node": "d",
                  "type": "field-end",
                  "subtype": "eq"
                },
                {
                  "node": "d",
                  "type": "cell-end"
                },
                {
                  "node": "d",
                  "type": "line-start",
                  "ref": "P429498.15",
                  "n": "11'",
                  "label": "o i' 11'"
                },
                {
                  "node": "d",
                  "type": "cell-start"
                },
                {
                  "node": "d",
                  "type": "field-start",
                  "subtype": "wp"
                },
                {
                  "node": "l",
                  "frag": "[...]",
                  "id": "P429498.l2fdf4",
                  "ref": "P429498.15.1",
                  "inst": "%sux:x=",
                  "f": {
                    "lang": "sux",
                    "form": "x",
                    "gdl": [
                      {
                        "x": "ellipsis",
                        "id": "P429498.15.1.0",
                        "breakStart": "1",
                        "break": "missing",
                        "o": "]",
                        "breakEnd": "P429498.15.1.0"
                      }
                    ]
                  }
                },
                {
                  "node": "d",
                  "type": "field-end",
                  "subtype": "wp"
                },
                {
                  "node": "d",
                  "type": "cell-end"
                },
                {
                  "node": "d",
                  "type": "cell-start"
                },
                {
                  "node": "d",
                  "type": "field-start",
                  "subtype": "eq"
                },
                {
                  "node": "l",
                  "frag": "[...]-pi",
                  "id": "P429498.l2fdf5",
                  "ref": "P429498.15.2",
                  "inst": "%akk-x-mbperi:x-pi=",
                  "f": {
                    "lang": "akk-x-mbperi",
                    "form": "x-pi",
                    "gdl": [
                      {
                        "x": "ellipsis",
                        "id": "P429498.15.2.0",
                        "breakStart": "1",
                        "break": "missing",
                        "o": "]",
                        "breakEnd": "P429498.15.2.0",
                        "delim": "-"
                      },
                      {
                        "v": "pi",
                        "id": "P429498.15.2.1"
                      }
                    ]
                  }
                },
                {
                  "node": "d",
                  "type": "field-end",
                  "subtype": "eq"
                },
                {
                  "node": "d",
                  "type": "cell-end"
                },
                {
                  "node": "d",
                  "type": "nonx",
                  "ref": "P429498.16",
                  "strict": "0",
                  "extent": "rest",
                  "state": "missing"
                },
                {
                  "node": "d",
                  "subtype": "column 2o '",
                  "type": "column",
                  "ref": "P429498.o.ii_.17",
                  "n": "2",
                  "label": "o ii'"
                },
                {
                  "node": "d",
                  "type": "nonx",
                  "ref": "P429498.18",
                  "strict": "0",
                  "extent": "beginning",
                  "state": "missing"
                },
                {
                  "node": "d",
                  "type": "line-start",
                  "ref": "P429498.19",
                  "n": "1'",
                  "label": "o ii' 1'"
                },
                {
                  "node": "d",
                  "type": "cell-start"
                },
                {
                  "node": "d",
                  "type": "field-start",
                  "subtype": "wp"
                },
                {
                  "node": "l",
                  "frag": "{lu₂}⸢x⸣-[...]",
                  "id": "P429498.l2fdf6",
                  "ref": "P429498.19.1",
                  "inst": "%sux:{lu₂}x-x=",
                  "f": {
                    "lang": "sux",
                    "form": "{lu₂}x-x",
                    "gdl": [
                      {
                        "det": "semantic",
                        "pos": "pre",
                        "seq": [
                          {
                            "v": "lu₂",
                            "id": "P429498.19.1.0"
                          }
                        ]
                      },
                      {
                        "v": "x",
                        "id": "P429498.19.1.1",
                        "break": "damaged",
                        "ho": "1",
                        "delim": "-",
                        "hc": "1"
                      },
                      {
                        "x": "ellipsis",
                        "id": "P429498.19.1.2",
                        "breakStart": "1",
                        "break": "missing",
                        "o": "]",
                        "breakEnd": "P429498.19.1.2"
                      }
                    ]
                  }
                },
                {
                  "node": "d",
                  "type": "field-end",
                  "subtype": "wp"
                },
                {
                  "node": "d",
                  "type": "cell-end"
                },
                {
                  "node": "d",
                  "type": "cell-start"
                },
                {
                  "node": "d",
                  "type": "field-start",
                  "subtype": "eq"
                },
                {
                  "node": "l",
                  "frag": "[...]",
                  "id": "P429498.l2fdf7",
                  "ref": "P429498.19.2",
                  "inst": "%akk-x-mbperi:x=",
                  "f": {
                    "lang": "akk-x-mbperi",
                    "form": "x",
                    "gdl": [
                      {
                        "x": "ellipsis",
                        "id": "P429498.19.2.0",
                        "breakStart": "1",
                        "break": "missing",
                        "o": "]",
                        "breakEnd": "P429498.19.2.0"
                      }
                    ]
                  }
                },
                {
                  "node": "d",
                  "type": "field-end",
                  "subtype": "eq"
                },
                {
                  "node": "d",
                  "type": "cell-end"
                },
                {
                  "node": "d",
                  "type": "line-start",
                  "ref": "P429498.20",
                  "n": "2'",
                  "label": "o ii' 2'"
                },
                {
                  "node": "d",
                  "type": "cell-start"
                },
                {
                  "node": "d",
                  "type": "field-start",
                  "subtype": "wp"
                },
                {
                  "node": "l",
                  "frag": "{lu₂}kal-[la]",
                  "id": "P429498.l2fdf8",
                  "ref": "P429498.20.1",
                  "inst": "%sux:{lu₂}kal-la=",
                  "f": {
                    "lang": "sux",
                    "form": "{lu₂}kal-la",
                    "gdl": [
                      {
                        "det": "semantic",
                        "pos": "pre",
                        "seq": [
                          {
                            "v": "lu₂",
                            "id": "P429498.20.1.0"
                          }
                        ]
                      },
                      {
                        "v": "kal",
                        "id": "P429498.20.1.1",
                        "delim": "-"
                      },
                      {
                        "v": "la",
                        "id": "P429498.20.1.2",
                        "breakStart": "1",
                        "o": "]",
                        "break": "missing",
                        "breakEnd": "P429498.20.1.2"
                      }
                    ]
                  }
                },
                {
                  "node": "d",
                  "type": "field-end",
                  "subtype": "wp"
                },
                {
                  "node": "d",
                  "type": "cell-end"
                },
                {
                  "node": "d",
                  "type": "cell-start"
                },
                {
                  "node": "d",
                  "type": "field-start",
                  "subtype": "eq"
                },
                {
                  "node": "l",
                  "frag": "[...]",
                  "id": "P429498.l2fdf9",
                  "ref": "P429498.20.2",
                  "inst": "%akk-x-mbperi:x=",
                  "f": {
                    "lang": "akk-x-mbperi",
                    "form": "x",
                    "gdl": [
                      {
                        "x": "ellipsis",
                        "id": "P429498.20.2.0",
                        "breakStart": "1",
                        "break": "missing",
                        "o": "]",
                        "breakEnd": "P429498.20.2.0"
                      }
                    ]
                  }
                },
                {
                  "node": "d",
                  "type": "field-end",
                  "subtype": "eq"
                },
                {
                  "node": "d",
                  "type": "cell-end"
                },
                {
                  "node": "d",
                  "type": "line-start",
                  "ref": "P429498.21",
                  "n": "3'",
                  "label": "o ii' 3'"
                },
                {
                  "node": "d",
                  "type": "cell-start"
                },
                {
                  "node": "d",
                  "type": "field-start",
                  "subtype": "wp"
                },
                {
                  "node": "l",
                  "frag": "{lu₂}saŋ-[kal]",
                  "id": "P429498.l2fdfa",
                  "ref": "P429498.21.1",
                  "inst": "%sux:{lu₂}saŋ-kal=",
                  "f": {
                    "lang": "sux",
                    "form": "{lu₂}saŋ-kal",
                    "gdl": [
                      {
                        "det": "semantic",
                        "pos": "pre",
                        "seq": [
                          {
                            "v": "lu₂",
                            "id": "P429498.21.1.0"
                          }
                        ]
                      },
                      {
                        "v": "saŋ",
                        "id": "P429498.21.1.1",
                        "delim": "-"
                      },
                      {
                        "v": "kal",
                        "id": "P429498.21.1.2",
                        "breakStart": "1",
                        "o": "]",
                        "queried": "1",
                        "break": "missing",
                        "breakEnd": "P429498.21.1.2"
                      }
                    ]
                  }
                },
                {
                  "node": "d",
                  "type": "field-end",
                  "subtype": "wp"
                },
                {
                  "node": "d",
                  "type": "cell-end"
                },
                {
                  "node": "d",
                  "type": "cell-start"
                },
                {
                  "node": "d",
                  "type": "field-start",
                  "subtype": "eq"
                },
                {
                  "node": "l",
                  "frag": "[...]",
                  "id": "P429498.l2fdfb",
                  "ref": "P429498.21.2",
                  "inst": "%akk-x-mbperi:x=",
                  "f": {
                    "lang": "akk-x-mbperi",
                    "form": "x",
                    "gdl": [
                      {
                        "x": "ellipsis",
                        "id": "P429498.21.2.0",
                        "breakStart": "1",
                        "break": "missing",
                        "o": "]",
                        "breakEnd": "P429498.21.2.0"
                      }
                    ]
                  }
                },
                {
                  "node": "d",
                  "type": "field-end",
                  "subtype": "eq"
                },
                {
                  "node": "d",
                  "type": "cell-end"
                },
                {
                  "node": "d",
                  "type": "line-start",
                  "ref": "P429498.22",
                  "n": "4'",
                  "label": "o ii' 4'"
                },
                {
                  "node": "d",
                  "type": "cell-start"
                },
                {
                  "node": "d",
                  "type": "field-start",
                  "subtype": "wp"
                },
                {
                  "node": "l",
                  "frag": "{lu₂}niŋ₂-[tuku]",
                  "id": "P429498.l2fdfc",
                  "ref": "P429498.22.1",
                  "inst": "%sux:{lu₂}niŋ₂-tuku=",
                  "f": {
                    "lang": "sux",
                    "form": "{lu₂}niŋ₂-tuku",
                    "gdl": [
                      {
                        "det": "semantic",
                        "pos": "pre",
                        "seq": [
                          {
                            "v": "lu₂",
                            "id": "P429498.22.1.0"
                          }
                        ]
                      },
                      {
                        "v": "niŋ₂",
                        "id": "P429498.22.1.1",
                        "delim": "-"
                      },
                      {
                        "v": "tuku",
                        "id": "P429498.22.1.2",
                        "breakStart": "1",
                        "o": "]",
                        "queried": "1",
                        "break": "missing",
                        "breakEnd": "P429498.22.1.2"
                      }
                    ]
                  }
                },
                {
                  "node": "d",
                  "type": "field-end",
                  "subtype": "wp"
                },
                {
                  "node": "d",
                  "type": "cell-end"
                },
                {
                  "node": "d",
                  "type": "cell-start"
                },
                {
                  "node": "d",
                  "type": "field-start",
                  "subtype": "eq"
                },
                {
                  "node": "l",
                  "frag": "[...]",
                  "id": "P429498.l2fdfd",
                  "ref": "P429498.22.2",
                  "inst": "%akk-x-mbperi:x=",
                  "f": {
                    "lang": "akk-x-mbperi",
                    "form": "x",
                    "gdl": [
                      {
                        "x": "ellipsis",
                        "id": "P429498.22.2.0",
                        "breakStart": "1",
                        "break": "missing",
                        "o": "]",
                        "breakEnd": "P429498.22.2.0"
                      }
                    ]
                  }
                },
                {
                  "node": "d",
                  "type": "field-end",
                  "subtype": "eq"
                },
                {
                  "node": "d",
                  "type": "cell-end"
                },
                {
                  "node": "d",
                  "type": "line-start",
                  "ref": "P429498.23",
                  "n": "5'",
                  "label": "o ii' 5'"
                },
                {
                  "node": "d",
                  "type": "cell-start"
                },
                {
                  "node": "d",
                  "type": "field-start",
                  "subtype": "wp"
                },
                {
                  "node": "l",
                  "frag": "{lu₂}ša-⸢x⸣",
                  "id": "P429498.l2fdfe",
                  "ref": "P429498.23.1",
                  "inst": "%sux:{lu₂}ša-x=",
                  "f": {
                    "lang": "sux",
                    "form": "{lu₂}ša-x",
                    "gdl": [
                      {
                        "det": "semantic",
                        "pos": "pre",
                        "seq": [
                          {
                            "v": "lu₂",
                            "id": "P429498.23.1.0"
                          }
                        ]
                      },
                      {
                        "v": "ša",
                        "id": "P429498.23.1.1",
                        "delim": "-"
                      },
                      {
                        "v": "x",
                        "id": "P429498.23.1.2",
                        "break": "damaged",
                        "ho": "1",
                        "hc": "1"
                      }
                    ]
                  }
                },
                {
                  "node": "d",
                  "type": "field-end",
                  "subtype": "wp"
                },
                {
                  "node": "d",
                  "type": "cell-end"
                },
                {
                  "node": "d",
                  "type": "cell-start"
                },
                {
                  "node": "d",
                  "type": "field-start",
                  "subtype": "eq"
                },
                {
                  "node": "l",
                  "frag": "[...]",
                  "id": "P429498.l2fdff",
                  "ref": "P429498.23.2",
                  "inst": "%akk-x-mbperi:x=",
                  "f": {
                    "lang": "akk-x-mbperi",
                    "form": "x",
                    "gdl": [
                      {
                        "x": "ellipsis",
                        "id": "P429498.23.2.0",
                        "breakStart": "1",
                        "break": "missing",
                        "o": "]",
                        "breakEnd": "P429498.23.2.0"
                      }
                    ]
                  }
                },
                {
                  "node": "d",
                  "type": "field-end",
                  "subtype": "eq"
                },
                {
                  "node": "d",
                  "type": "cell-end"
                },
                {
                  "node": "d",
                  "type": "line-start",
                  "ref": "P429498.24",
                  "n": "6'",
                  "label": "o ii' 6'"
                },
                {
                  "node": "d",
                  "type": "cell-start"
                },
                {
                  "node": "d",
                  "type": "field-start",
                  "subtype": "wp"
                },
                {
                  "node": "l",
                  "frag": "{lu₂}|MAŠ.EN.KAK|",
                  "id": "P429498.l2fe00",
                  "ref": "P429498.24.1",
                  "inst": "%sux:{lu₂}|MAŠ.EN.KAK|=",
                  "f": {
                    "lang": "sux",
                    "form": "{lu₂}|MAŠ.EN.KAK|",
                    "gdl": [
                      {
                        "det": "semantic",
                        "pos": "pre",
                        "seq": [
                          {
                            "v": "lu₂",
                            "id": "P429498.24.1.0"
                          }
                        ]
                      },
                      {
                        "c": "|MAŠ.EN.KAK|",
                        "id": "P429498.24.1.1",
                        "seq": [
                          {
                            "s": "MAŠ"
                          },
                          {
                            "o": "beside"
                          },
                          {
                            "s": "EN"
                          },
                          {
                            "o": "beside"
                          },
                          {
                            "s": "KAK",
                            "break": "damaged"
                          }
                        ]
                      }
                    ]
                  }
                },
                {
                  "node": "d",
                  "type": "field-end",
                  "subtype": "wp"
                },
                {
                  "node": "d",
                  "type": "cell-end"
                },
                {
                  "node": "d",
                  "type": "cell-start"
                },
                {
                  "node": "d",
                  "type": "field-start",
                  "subtype": "eq"
                },
                {
                  "node": "l",
                  "frag": "[...]",
                  "id": "P429498.l2fe01",
                  "ref": "P429498.24.2",
                  "inst": "%akk-x-mbperi:x=",
                  "f": {
                    "lang": "akk-x-mbperi",
                    "form": "x",
                    "gdl": [
                      {
                        "x": "ellipsis",
                        "id": "P429498.24.2.0",
                        "breakStart": "1",
                        "break": "missing",
                        "o": "]",
                        "breakEnd": "P429498.24.2.0"
                      }
                    ]
                  }
                },
                {
                  "node": "d",
                  "type": "field-end",
                  "subtype": "eq"
                },
                {
                  "node": "d",
                  "type": "cell-end"
                },
                {
                  "node": "d",
                  "type": "line-start",
                  "ref": "P429498.25",
                  "n": "7'",
                  "label": "o ii' 7'"
                },
                {
                  "node": "d",
                  "type": "cell-start"
                },
                {
                  "node": "d",
                  "type": "field-start",
                  "subtype": "wp"
                },
                {
                  "node": "l",
                  "frag": "{lu₂}saŋ-kur-⸢ta⸣",
                  "id": "P429498.l2fe02",
                  "ref": "P429498.25.1",
                  "inst": "%sux:{lu₂}saŋ-kur-ta=",
                  "f": {
                    "lang": "sux",
                    "form": "{lu₂}saŋ-kur-ta",
                    "gdl": [
                      {
                        "det": "semantic",
                        "pos": "pre",
                        "seq": [
                          {
                            "v": "lu₂",
                            "id": "P429498.25.1.0"
                          }
                        ]
                      },
                      {
                        "v": "saŋ",
                        "id": "P429498.25.1.1",
                        "delim": "-"
                      },
                      {
                        "v": "kur",
                        "id": "P429498.25.1.2",
                        "delim": "-"
                      },
                      {
                        "v": "ta",
                        "id": "P429498.25.1.3",
                        "break": "damaged",
                        "ho": "1",
                        "hc": "1"
                      }
                    ]
                  }
                },
                {
                  "node": "d",
                  "type": "field-end",
                  "subtype": "wp"
                },
                {
                  "node": "d",
                  "type": "cell-end"
                },
                {
                  "node": "d",
                  "type": "cell-start"
                },
                {
                  "node": "d",
                  "type": "field-start",
                  "subtype": "eq"
                },
                {
                  "node": "l",
                  "frag": "[...]",
                  "id": "P429498.l2fe03",
                  "ref": "P429498.25.2",
                  "inst": "%akk-x-mbperi:x=",
                  "f": {
                    "lang": "akk-x-mbperi",
                    "form": "x",
                    "gdl": [
                      {
                        "x": "ellipsis",
                        "id": "P429498.25.2.0",
                        "breakStart": "1",
                        "break": "missing",
                        "o": "]",
                        "breakEnd": "P429498.25.2.0"
                      }
                    ]
                  }
                },
                {
                  "node": "d",
                  "type": "field-end",
                  "subtype": "eq"
                },
                {
                  "node": "d",
                  "type": "cell-end"
                },
                {
                  "node": "d",
                  "type": "line-start",
                  "ref": "P429498.26",
                  "n": "8'",
                  "label": "o ii' 8'"
                },
                {
                  "node": "d",
                  "type": "cell-start"
                },
                {
                  "node": "d",
                  "type": "field-start",
                  "subtype": "wp"
                },
                {
                  "node": "l",
                  "frag": "{lu₂}mu-uš-⸢ke⸣-[nu]",
                  "id": "P429498.l2fe04",
                  "ref": "P429498.26.1",
                  "inst": "%sux:{lu₂}mu-uš-ke-nu=",
                  "f": {
                    "lang": "sux",
                    "form": "{lu₂}mu-uš-ke-nu",
                    "gdl": [
                      {
                        "det": "semantic",
                        "pos": "pre",
                        "seq": [
                          {
                            "v": "lu₂",
                            "id": "P429498.26.1.0"
                          }
                        ]
                      },
                      {
                        "v": "mu",
                        "id": "P429498.26.1.1",
                        "delim": "-"
                      },
                      {
                        "v": "uš",
                        "id": "P429498.26.1.2",
                        "delim": "-"
                      },
                      {
                        "v": "ke",
                        "id": "P429498.26.1.3",
                        "break": "damaged",
                        "queried": "1",
                        "ho": "1",
                        "delim": "-",
                        "hc": "1"
                      },
                      {
                        "v": "nu",
                        "id": "P429498.26.1.4",
                        "breakStart": "1",
                        "o": "]",
                        "break": "missing",
                        "breakEnd": "P429498.26.1.4"
                      }
                    ]
                  }
                },
                {
                  "node": "d",
                  "type": "field-end",
                  "subtype": "wp"
                },
                {
                  "node": "d",
                  "type": "cell-end"
                },
                {
                  "node": "d",
                  "type": "cell-start"
                },
                {
                  "node": "d",
                  "type": "field-start",
                  "subtype": "eq"
                },
                {
                  "node": "l",
                  "frag": "[...]",
                  "id": "P429498.l2fe05",
                  "ref": "P429498.26.2",
                  "inst": "%akk-x-mbperi:x=",
                  "f": {
                    "lang": "akk-x-mbperi",
                    "form": "x",
                    "gdl": [
                      {
                        "x": "ellipsis",
                        "id": "P429498.26.2.0",
                        "breakStart": "1",
                        "break": "missing",
                        "o": "]",
                        "breakEnd": "P429498.26.2.0"
                      }
                    ]
                  }
                },
                {
                  "node": "d",
                  "type": "field-end",
                  "subtype": "eq"
                },
                {
                  "node": "d",
                  "type": "cell-end"
                },
                {
                  "node": "d",
                  "type": "line-start",
                  "ref": "P429498.27",
                  "n": "9'",
                  "label": "o ii' 9'"
                },
                {
                  "node": "d",
                  "type": "cell-start"
                },
                {
                  "node": "d",
                  "type": "field-start",
                  "subtype": "wp"
                },
                {
                  "node": "l",
                  "frag": "{lu₂}ba-⸢ba⸣",
                  "id": "P429498.l2fe06",
                  "ref": "P429498.27.1",
                  "inst": "%sux:{lu₂}ba-ba=",
                  "f": {
                    "lang": "sux",
                    "form": "{lu₂}ba-ba",
                    "gdl": [
                      {
                        "det": "semantic",
                        "pos": "pre",
                        "seq": [
                          {
                            "v": "lu₂",
                            "id": "P429498.27.1.0"
                          }
                        ]
                      },
                      {
                        "v": "ba",
                        "id": "P429498.27.1.1",
                        "delim": "-"
                      },
                      {
                        "v": "ba",
                        "id": "P429498.27.1.2",
                        "break": "damaged",
                        "queried": "1",
                        "ho": "1",
                        "hc": "1"
                      }
                    ]
                  }
                },
                {
                  "node": "d",
                  "type": "field-end",
                  "subtype": "wp"
                },
                {
                  "node": "d",
                  "type": "cell-end"
                },
                {
                  "node": "d",
                  "type": "cell-start"
                },
                {
                  "node": "d",
                  "type": "field-start",
                  "subtype": "eq"
                },
                {
                  "node": "l",
                  "frag": "[...]",
                  "id": "P429498.l2fe07",
                  "ref": "P429498.27.2",
                  "inst": "%akk-x-mbperi:x=",
                  "f": {
                    "lang": "akk-x-mbperi",
                    "form": "x",
                    "gdl": [
                      {
                        "x": "ellipsis",
                        "id": "P429498.27.2.0",
                        "breakStart": "1",
                        "break": "missing",
                        "o": "]",
                        "breakEnd": "P429498.27.2.0"
                      }
                    ]
                  }
                },
                {
                  "node": "d",
                  "type": "field-end",
                  "subtype": "eq"
                },
                {
                  "node": "d",
                  "type": "cell-end"
                },
                {
                  "node": "d",
                  "type": "line-start",
                  "ref": "P429498.28",
                  "n": "10'",
                  "label": "o ii' 10'"
                },
                {
                  "node": "d",
                  "type": "cell-start"
                },
                {
                  "node": "d",
                  "type": "field-start",
                  "subtype": "wp"
                },
                {
                  "node": "l",
                  "frag": "{lu₂}saŋ-kur",
                  "id": "P429498.l2fe08",
                  "ref": "P429498.28.1",
                  "inst": "%sux:{lu₂}saŋ-kur=",
                  "f": {
                    "lang": "sux",
                    "form": "{lu₂}saŋ-kur",
                    "gdl": [
                      {
                        "det": "semantic",
                        "pos": "pre",
                        "seq": [
                          {
                            "v": "lu₂",
                            "id": "P429498.28.1.0"
                          }
                        ]
                      },
                      {
                        "v": "saŋ",
                        "id": "P429498.28.1.1",
                        "delim": "-"
                      },
                      {
                        "v": "kur",
                        "id": "P429498.28.1.2"
                      }
                    ]
                  }
                },
                {
                  "node": "d",
                  "type": "field-end",
                  "subtype": "wp"
                },
                {
                  "node": "d",
                  "type": "cell-end"
                },
                {
                  "node": "d",
                  "type": "cell-start"
                },
                {
                  "node": "d",
                  "type": "field-start",
                  "subtype": "eq"
                },
                {
                  "node": "l",
                  "frag": "[...]",
                  "id": "P429498.l2fe09",
                  "ref": "P429498.28.2",
                  "inst": "%akk-x-mbperi:x=",
                  "f": {
                    "lang": "akk-x-mbperi",
                    "form": "x",
                    "gdl": [
                      {
                        "x": "ellipsis",
                        "id": "P429498.28.2.0",
                        "breakStart": "1",
                        "break": "missing",
                        "o": "]",
                        "breakEnd": "P429498.28.2.0"
                      }
                    ]
                  }
                },
                {
                  "node": "d",
                  "type": "field-end",
                  "subtype": "eq"
                },
                {
                  "node": "d",
                  "type": "cell-end"
                },
                {
                  "node": "d",
                  "type": "line-start",
                  "ref": "P429498.29",
                  "n": "11'",
                  "label": "o ii' 11'"
                },
                {
                  "node": "d",
                  "type": "cell-start"
                },
                {
                  "node": "d",
                  "type": "field-start",
                  "subtype": "wp"
                },
                {
                  "node": "l",
                  "frag": "{lu₂}la-[x]",
                  "id": "P429498.l2fe0a",
                  "ref": "P429498.29.1",
                  "inst": "%sux:{lu₂}la-x=",
                  "f": {
                    "lang": "sux",
                    "form": "{lu₂}la-x",
                    "gdl": [
                      {
                        "det": "semantic",
                        "pos": "pre",
                        "seq": [
                          {
                            "v": "lu₂",
                            "id": "P429498.29.1.0"
                          }
                        ]
                      },
                      {
                        "v": "la",
                        "id": "P429498.29.1.1",
                        "delim": "-"
                      },
                      {
                        "v": "x",
                        "id": "P429498.29.1.2",
                        "breakStart": "1",
                        "o": "]",
                        "break": "missing",
                        "breakEnd": "P429498.29.1.2"
                      }
                    ]
                  }
                },
                {
                  "node": "d",
                  "type": "field-end",
                  "subtype": "wp"
                },
                {
                  "node": "d",
                  "type": "cell-end"
                },
                {
                  "node": "d",
                  "type": "cell-start"
                },
                {
                  "node": "d",
                  "type": "field-start",
                  "subtype": "eq"
                },
                {
                  "node": "l",
                  "frag": "[...]",
                  "id": "P429498.l2fe0b",
                  "ref": "P429498.29.2",
                  "inst": "%akk-x-mbperi:x=",
                  "f": {
                    "lang": "akk-x-mbperi",
                    "form": "x",
                    "gdl": [
                      {
                        "x": "ellipsis",
                        "id": "P429498.29.2.0",
                        "breakStart": "1",
                        "break": "missing",
                        "o": "]",
                        "breakEnd": "P429498.29.2.0"
                      }
                    ]
                  }
                },
                {
                  "node": "d",
                  "type": "field-end",
                  "subtype": "eq"
                },
                {
                  "node": "d",
                  "type": "cell-end"
                },
                {
                  "node": "d",
                  "type": "line-start",
                  "ref": "P429498.30",
                  "n": "12'",
                  "label": "o ii' 12'"
                },
                {
                  "node": "d",
                  "type": "cell-start"
                },
                {
                  "node": "d",
                  "type": "field-start",
                  "subtype": "wp"
                },
                {
                  "node": "l",
                  "frag": "{lu₂}ib-[x]",
                  "id": "P429498.l2fe0c",
                  "ref": "P429498.30.1",
                  "inst": "%sux:{lu₂}ib-x=",
                  "f": {
                    "lang": "sux",
                    "form": "{lu₂}ib-x",
                    "gdl": [
                      {
                        "det": "semantic",
                        "pos": "pre",
                        "seq": [
                          {
                            "v": "lu₂",
                            "id": "P429498.30.1.0"
                          }
                        ]
                      },
                      {
                        "v": "ib",
                        "id": "P429498.30.1.1",
                        "delim": "-"
                      },
                      {
                        "v": "x",
                        "id": "P429498.30.1.2",
                        "breakStart": "1",
                        "o": "]",
                        "break": "missing",
                        "breakEnd": "P429498.30.1.2"
                      }
                    ]
                  }
                },
                {
                  "node": "d",
                  "type": "field-end",
                  "subtype": "wp"
                },
                {
                  "node": "d",
                  "type": "cell-end"
                },
                {
                  "node": "d",
                  "type": "cell-start"
                },
                {
                  "node": "d",
                  "type": "field-start",
                  "subtype": "eq"
                },
                {
                  "node": "l",
                  "frag": "[...]",
                  "id": "P429498.l2fe0d",
                  "ref": "P429498.30.2",
                  "inst": "%akk-x-mbperi:x=",
                  "f": {
                    "lang": "akk-x-mbperi",
                    "form": "x",
                    "gdl": [
                      {
                        "x": "ellipsis",
                        "id": "P429498.30.2.0",
                        "breakStart": "1",
                        "break": "missing",
                        "o": "]",
                        "breakEnd": "P429498.30.2.0"
                      }
                    ]
                  }
                },
                {
                  "node": "d",
                  "type": "field-end",
                  "subtype": "eq"
                },
                {
                  "node": "d",
                  "type": "cell-end"
                },
                {
                  "node": "d",
                  "type": "line-start",
                  "ref": "P429498.31",
                  "n": "13'",
                  "label": "o ii' 13'"
                },
                {
                  "node": "d",
                  "type": "cell-start"
                },
                {
                  "node": "d",
                  "type": "field-start",
                  "subtype": "wp"
                },
                {
                  "node": "l",
                  "frag": "{lu₂}ib-⸢si⸣-[sa₂]",
                  "id": "P429498.l2fe0e",
                  "ref": "P429498.31.1",
                  "inst": "%sux:{lu₂}ib-si-sa₂=",
                  "f": {
                    "lang": "sux",
                    "form": "{lu₂}ib-si-sa₂",
                    "gdl": [
                      {
                        "det": "semantic",
                        "pos": "pre",
                        "seq": [
                          {
                            "v": "lu₂",
                            "id": "P429498.31.1.0"
                          }
                        ]
                      },
                      {
                        "v": "ib",
                        "id": "P429498.31.1.1",
                        "delim": "-"
                      },
                      {
                        "v": "si",
                        "id": "P429498.31.1.2",
                        "break": "damaged",
                        "ho": "1",
                        "delim": "-",
                        "hc": "1"
                      },
                      {
                        "v": "sa₂",
                        "id": "P429498.31.1.3",
                        "breakStart": "1",
                        "o": "]",
                        "queried": "1",
                        "break": "missing",
                        "breakEnd": "P429498.31.1.3"
                      }
                    ]
                  }
                },
                {
                  "node": "d",
                  "type": "field-end",
                  "subtype": "wp"
                },
                {
                  "node": "d",
                  "type": "cell-end"
                },
                {
                  "node": "d",
                  "type": "cell-start"
                },
                {
                  "node": "d",
                  "type": "field-start",
                  "subtype": "eq"
                },
                {
                  "node": "l",
                  "frag": "[...]",
                  "id": "P429498.l2fe0f",
                  "ref": "P429498.31.2",
                  "inst": "%akk-x-mbperi:x=",
                  "f": {
                    "lang": "akk-x-mbperi",
                    "form": "x",
                    "gdl": [
                      {
                        "x": "ellipsis",
                        "id": "P429498.31.2.0",
                        "breakStart": "1",
                        "break": "missing",
                        "o": "]",
                        "breakEnd": "P429498.31.2.0"
                      }
                    ]
                  }
                },
                {
                  "node": "d",
                  "type": "field-end",
                  "subtype": "eq"
                },
                {
                  "node": "d",
                  "type": "cell-end"
                },
                {
                  "node": "d",
                  "type": "line-start",
                  "ref": "P429498.32",
                  "n": "14'",
                  "label": "o ii' 14'"
                },
                {
                  "node": "d",
                  "type": "cell-start"
                },
                {
                  "node": "d",
                  "type": "field-start",
                  "subtype": "wp"
                },
                {
                  "node": "l",
                  "frag": "{lu₂}ib-zi-[x]",
                  "id": "P429498.l2fe10",
                  "ref": "P429498.32.1",
                  "inst": "%sux:{lu₂}ib-zi-x=",
                  "f": {
                    "lang": "sux",
                    "form": "{lu₂}ib-zi-x",
                    "gdl": [
                      {
                        "det": "semantic",
                        "pos": "pre",
                        "seq": [
                          {
                            "v": "lu₂",
                            "id": "P429498.32.1.0"
                          }
                        ]
                      },
                      {
                        "v": "ib",
                        "id": "P429498.32.1.1",
                        "delim": "-"
                      },
                      {
                        "v": "zi",
                        "id": "P429498.32.1.2",
                        "delim": "-"
                      },
                      {
                        "v": "x",
                        "id": "P429498.32.1.3",
                        "breakStart": "1",
                        "o": "]",
                        "break": "missing",
                        "breakEnd": "P429498.32.1.3"
                      }
                    ]
                  }
                },
                {
                  "node": "d",
                  "type": "field-end",
                  "subtype": "wp"
                },
                {
                  "node": "d",
                  "type": "cell-end"
                },
                {
                  "node": "d",
                  "type": "cell-start"
                },
                {
                  "node": "d",
                  "type": "field-start",
                  "subtype": "eq"
                },
                {
                  "node": "l",
                  "frag": "[...]",
                  "id": "P429498.l2fe11",
                  "ref": "P429498.32.2",
                  "inst": "%akk-x-mbperi:x=",
                  "f": {
                    "lang": "akk-x-mbperi",
                    "form": "x",
                    "gdl": [
                      {
                        "x": "ellipsis",
                        "id": "P429498.32.2.0",
                        "breakStart": "1",
                        "break": "missing",
                        "o": "]",
                        "breakEnd": "P429498.32.2.0"
                      }
                    ]
                  }
                },
                {
                  "node": "d",
                  "type": "field-end",
                  "subtype": "eq"
                },
                {
                  "node": "d",
                  "type": "cell-end"
                },
                {
                  "node": "d",
                  "type": "line-start",
                  "ref": "P429498.33",
                  "n": "15'",
                  "label": "o ii' 15'"
                },
                {
                  "node": "d",
                  "type": "cell-start"
                },
                {
                  "node": "d",
                  "type": "field-start",
                  "subtype": "wp"
                },
                {
                  "node": "l",
                  "frag": "{lu₂}ib-[x]",
                  "id": "P429498.l2fe12",
                  "ref": "P429498.33.1",
                  "inst": "%sux:{lu₂}ib-x=",
                  "f": {
                    "lang": "sux",
                    "form": "{lu₂}ib-x",
                    "gdl": [
                      {
                        "det": "semantic",
                        "pos": "pre",
                        "seq": [
                          {
                            "v": "lu₂",
                            "id": "P429498.33.1.0"
                          }
                        ]
                      },
                      {
                        "v": "ib",
                        "id": "P429498.33.1.1",
                        "delim": "-"
                      },
                      {
                        "v": "x",
                        "id": "P429498.33.1.2",
                        "breakStart": "1",
                        "o": "]",
                        "break": "missing",
                        "breakEnd": "P429498.33.1.2"
                      }
                    ]
                  }
                },
                {
                  "node": "d",
                  "type": "field-end",
                  "subtype": "wp"
                },
                {
                  "node": "d",
                  "type": "cell-end"
                },
                {
                  "node": "d",
                  "type": "cell-start"
                },
                {
                  "node": "d",
                  "type": "field-start",
                  "subtype": "eq"
                },
                {
                  "node": "l",
                  "frag": "[...]",
                  "id": "P429498.l2fe13",
                  "ref": "P429498.33.2",
                  "inst": "%akk-x-mbperi:x=",
                  "f": {
                    "lang": "akk-x-mbperi",
                    "form": "x",
                    "gdl": [
                      {
                        "x": "ellipsis",
                        "id": "P429498.33.2.0",
                        "breakStart": "1",
                        "break": "missing",
                        "o": "]",
                        "breakEnd": "P429498.33.2.0"
                      }
                    ]
                  }
                },
                {
                  "node": "d",
                  "type": "field-end",
                  "subtype": "eq"
                },
                {
                  "node": "d",
                  "type": "cell-end"
                },
                {
                  "node": "d",
                  "type": "line-start",
                  "ref": "P429498.34",
                  "n": "16'",
                  "label": "o ii' 16'"
                },
                {
                  "node": "d",
                  "type": "cell-start"
                },
                {
                  "node": "d",
                  "type": "field-start",
                  "subtype": "wp"
                },
                {
                  "node": "l",
                  "frag": "{lu₂}a-⸢x⸣-[x]",
                  "id": "P429498.l2fe14",
                  "ref": "P429498.34.1",
                  "inst": "%sux:{lu₂}a-x-x=",
                  "f": {
                    "lang": "sux",
                    "form": "{lu₂}a-x-x",
                    "gdl": [
                      {
                        "det": "semantic",
                        "pos": "pre",
                        "seq": [
                          {
                            "v": "lu₂",
                            "id": "P429498.34.1.0"
                          }
                        ]
                      },
                      {
                        "v": "a",
                        "id": "P429498.34.1.1",
                        "delim": "-"
                      },
                      {
                        "v": "x",
                        "id": "P429498.34.1.2",
                        "break": "damaged",
                        "ho": "1",
                        "delim": "-",
                        "hc": "1"
                      },
                      {
                        "v": "x",
                        "id": "P429498.34.1.3",
                        "breakStart": "1",
                        "o": "]",
                        "break": "missing",
                        "breakEnd": "P429498.34.1.3"
                      }
                    ]
                  }
                },
                {
                  "node": "d",
                  "type": "field-end",
                  "subtype": "wp"
                },
                {
                  "node": "d",
                  "type": "cell-end"
                },
                {
                  "node": "d",
                  "type": "cell-start"
                },
                {
                  "node": "d",
                  "type": "field-start",
                  "subtype": "eq"
                },
                {
                  "node": "l",
                  "frag": "[...]",
                  "id": "P429498.l2fe15",
                  "ref": "P429498.34.2",
                  "inst": "%akk-x-mbperi:x=",
                  "f": {
                    "lang": "akk-x-mbperi",
                    "form": "x",
                    "gdl": [
                      {
                        "x": "ellipsis",
                        "id": "P429498.34.2.0",
                        "breakStart": "1",
                        "break": "missing",
                        "o": "]",
                        "breakEnd": "P429498.34.2.0"
                      }
                    ]
                  }
                },
                {
                  "node": "d",
                  "type": "field-end",
                  "subtype": "eq"
                },
                {
                  "node": "d",
                  "type": "cell-end"
                },
                {
                  "node": "d",
                  "type": "line-start",
                  "ref": "P429498.35",
                  "n": "17'",
                  "label": "o ii' 17'"
                },
                {
                  "node": "d",
                  "type": "cell-start"
                },
                {
                  "node": "d",
                  "type": "field-start",
                  "subtype": "wp"
                },
                {
                  "node": "l",
                  "frag": "{lu₂}za-⸢am⸣-[...]",
                  "id": "P429498.l2fe16",
                  "ref": "P429498.35.1",
                  "inst": "%sux:{lu₂}za-am-x=",
                  "f": {
                    "lang": "sux",
                    "form": "{lu₂}za-am-x",
                    "gdl": [
                      {
                        "det": "semantic",
                        "pos": "pre",
                        "seq": [
                          {
                            "v": "lu₂",
                            "id": "P429498.35.1.0"
                          }
                        ]
                      },
                      {
                        "v": "za",
                        "id": "P429498.35.1.1",
                        "delim": "-"
                      },
                      {
                        "v": "am",
                        "id": "P429498.35.1.2",
                        "break": "damaged",
                        "queried": "1",
                        "ho": "1",
                        "delim": "-",
                        "hc": "1"
                      },
                      {
                        "x": "ellipsis",
                        "id": "P429498.35.1.3",
                        "breakStart": "1",
                        "break": "missing",
                        "o": "]",
                        "breakEnd": "P429498.35.1.3"
                      }
                    ]
                  }
                },
                {
                  "node": "d",
                  "type": "field-end",
                  "subtype": "wp"
                },
                {
                  "node": "d",
                  "type": "cell-end"
                },
                {
                  "node": "d",
                  "type": "cell-start"
                },
                {
                  "node": "d",
                  "type": "field-start",
                  "subtype": "eq"
                },
                {
                  "node": "l",
                  "frag": "[...]",
                  "id": "P429498.l2fe17",
                  "ref": "P429498.35.2",
                  "inst": "%akk-x-mbperi:x=",
                  "f": {
                    "lang": "akk-x-mbperi",
                    "form": "x",
                    "gdl": [
                      {
                        "x": "ellipsis",
                        "id": "P429498.35.2.0",
                        "breakStart": "1",
                        "break": "missing",
                        "o": "]",
                        "breakEnd": "P429498.35.2.0"
                      }
                    ]
                  }
                },
                {
                  "node": "d",
                  "type": "field-end",
                  "subtype": "eq"
                },
                {
                  "node": "d",
                  "type": "cell-end"
                },
                {
                  "node": "d",
                  "type": "nonx",
                  "ref": "P429498.36",
                  "strict": "0",
                  "extent": "rest",
                  "state": "missing"
                },
                {
                  "node": "d",
                  "subtype": "reverse",
                  "type": "reverse",
                  "ref": "P429498.r.37",
                  "label": "r"
                },
                {
                  "node": "d",
                  "type": "nonx",
                  "ref": "P429498.38",
                  "strict": "1",
                  "extent": "n",
                  "scope": "line",
                  "state": "missing"
                }
              ]
            }
          ]
        }
      ]
    }
  ]
}
